drf_account/__init__.py
drf_account/admin.py
drf_account/apps.py
drf_account/models.py
drf_account/serializers.py
drf_account/tests.py
drf_account/urls.py
drf_account/views.py
drf_account/migrations/0001_initial.py
drf_account/migrations/0002_auto_20180717_1841.py
drf_account/migrations/__init__.py
drf_account-0.0.2.dist-info/METADATA
drf_account-0.0.2.dist-info/RECORD
drf_account-0.0.2.dist-info/WHEEL
drf_account-0.0.2.dist-info/top_level.txt
